{
  "module_id": "AG43A",
  "title": "Topic, Reference and Image Integration Readiness Record",
  "status": "ready_for_ag43b_topic_reference_image_integration",
  "ready_for_ag43b": true,
  "next_stage_id": "AG43B",
  "next_stage_title": "Topic, Reference and Image Governance Integration",
  "ag43a_entry_complete": true,
  "hard_blocker_count_for_ag43b": 0,
  "first_controlled_dynamic_content_loop_deferred_to_ag56": true,
  "ag43b_scope": "topic_reference_image_integration_only_no_article_generation",
  "deployment_allowed_next": false,
  "public_mutation_allowed_next": false,
  "real_publish_allowed_next": false,
  "database_write_allowed_next": false,
  "backend_activation_allowed_next": false,
  "service_role_key_required_in_repo_or_chat": false,
  "blocked_state": {
    "article_intelligence_integration_entry_created": true,
    "content_intelligence_consumption_map_created": true,
    "topic_engine_consumption_map_created": true,
    "article_quality_consumption_map_created": true,
    "integration_gap_register_created": true,
    "no_duplicate_audit_passed": true,
    "ag43b_topic_reference_image_integration_ready": true,
    "entry_only": true,
    "first_controlled_dynamic_content_loop_deferred_to_ag56": true,
    "topic_promoted_to_live_article": false,
    "article_generated": false,
    "article_file_created_or_changed": false,
    "article_quality_runtime_executed": false,
    "reference_fetch_executed": false,
    "image_generation_executed": false,
    "featured_reads_mutated": false,
    "homepage_mutated": false,
    "listing_mutated": false,
    "first_controlled_batch_execution_approved_now": false,
    "first_controlled_batch_executed": false,
    "batch_execution_authorized_now": false,
    "batch_publish_executed": false,
    "candidate_selected_for_execution": false,
    "public_mutation_approved_now": false,
    "execution_authorized_now": false,
    "real_publish_executed": false,
    "actual_queue_state_changed": false,
    "audit_log_write_done": false,
    "rollback_write_done": false,
    "database_write_done": false,
    "public_article_mutated": false,
    "route_guard_runtime_modified": false,
    "dashboard_runtime_enabled": false,
    "dashboard_data_query_executed": false,
    "monitoring_job_created": false,
    "deployment_triggered": false,
    "deployment_done": false,
    "public_mutation_done": false,
    "dynamic_publish_runtime_enabled": false,
    "backend_activation_approved_now": false,
    "supabase_activation_approved_now": false,
    "auth_activation_approved_now": false,
    "service_role_key_recorded": false,
    "service_role_key_exposed": false,
    "anon_access_granted": false,
    "write_grants_executed": false,
    "sql_file_created": false,
    "sql_grants_executed": false
  }
}
