{
  "module_id": "AG62Z",
  "status": "ag62z_first_light_working_data_closure_completed",
  "ag62a_foundation_completed": 1,
  "ag62b_ui_wiring_completed": 1,
  "generated_first_light_item_count": 10,
  "live_evidence_recorded": 1,
  "first_light_row_closed_at_working_data_level": 1,
  "real_news_engine_active": 0,
  "source_collection_active": 0,
  "ai_runtime_active": 0,
  "user_triggered_ai_allowed": 0,
  "backend_runtime_activated": 0,
  "service_role_used": 0,
  "v02_expansion_started": 0,
  "ready_for_ag63": 1
}
