{
  "module_id": "AG74H",
  "title": "Panchang Active UI QA Evidence",
  "status": "ag74h_active_ui_qa_evidence_clean",
  "checks": {
    "active_data_source_present_in_index": true,
    "ag74g_marker_present_in_index": true,
    "active_record_count": 12,
    "required_runtime_fields_present": true,
    "required_reference_locations_present": true,
    "backend_runtime_activated": false,
    "supabase_activation_performed": false,
    "personal_data_storage_enabled": false,
    "live_ephemeris_api_dependency_enabled": false
  },
  "issue_count": 0,
  "issues": []
}
