{
  "module_id": "AG56Z",
  "title": "Version 01 Live Closure Record",
  "status": "version_01_live_closure_completed_conditionally",
  "audit_passed": true,
  "closure_mode": "CONDITIONAL_GO_FOR_AG56Z_WITH_PRE_LIVE_DEFECT_LIST",
  "closure_statement": "AG56 controlled content loop is closed as conditional. Full public go-live remains blocked until the pre-live defect list is cleared or explicitly deferred through a separate governed decision.",
  "ag56_chain_closed": [
    "AG56.1",
    "AG56.2",
    "AG56.3",
    "AG56.4",
    "AG56.5",
    "AG56.6",
    "AG56.7",
    "AG56.8"
  ],
  "full_public_go_live_approved_now": false,
  "deployment_approved_now": false,
  "backend_runtime_approved_now": false,
  "v02_expansion_approved_now": false,
  "blocked_state": {
    "ag56z_version_01_live_closure_recorded": true,
    "ag56_1_to_ag56_8_consumed": true,
    "conditional_go_closure_recorded": true,
    "pre_live_defect_list_recorded": true,
    "final_live_closure_boundary_recorded": true,
    "post_closure_handoff_recorded": true,
    "pre_live_defect_clearance_readiness_recorded": true,
    "full_public_go_live_approved": false,
    "actual_live_declaration_approved": false,
    "deployment_approved": false,
    "deployment_performed": false,
    "actual_deployment_triggered": false,
    "vercel_deployment_triggered": false,
    "github_release_created": false,
    "live_public_check_executed": false,
    "browser_automation_enabled": false,
    "external_audit_api_enabled": false,
    "public_page_mutation_enabled": false,
    "public_content_mutation_enabled": false,
    "content_publishing_enabled": false,
    "homepage_live_updated": false,
    "live_listing_updated": false,
    "public_url_live": false,
    "backend_auth_supabase_activation_approved": false,
    "backend_auth_supabase_activation_performed": false,
    "service_role_key_used": false,
    "service_role_key_exposed": false,
    "rls_policy_mutation_enabled": false,
    "grant_mutation_enabled": false,
    "runtime_database_query_enabled": false,
    "website_database_reading_enabled": false,
    "api_runtime_database_reading_approved_now": false,
    "runtime_publish_queue_enabled": false,
    "runtime_cms_enabled": false,
    "public_dashboard_exposed": false,
    "automated_external_fetch_enabled": false,
    "rollback_operation_executed": false,
    "git_revert_executed": false,
    "git_reset_executed": false,
    "actual_go_live_approval_granted": false,
    "v02_item_activated": false
  }
}
