{
  "date": "2026-04-11",
  "category": "spirituality",
  "draft_packet": {
    "date": "2026-04-11",
    "meta_label": "Spirituality",
    "title": "The Role of Mindfulness in Modern Spiritual Practice",
    "slug": "role-of-mindfulness-in-modern-spiritual-practice",
    "subtitle": "Ancient mindfulness techniques enriching contemporary spirituality",
    "summary": "This article examines the resurgence of mindfulness within various spiritual traditions, analyzing its impact on individual mental health and community cohesion in an increasingly fast-paced world.",
    "image": "assets/featured/2026-04-11/spirituality/lead-1.jpg",
    "image_mode": "manual_asset_category",
    "image_path": "assets/featured/2026-04-11/spirituality/lead-1.jpg",
    "image_credit": "Drishvara Library",
    "image_source_url": "",
    "image_alt": "Spirituality visual for The Role of Mindfulness in Modern Spiritual Practice",
    "image_prompt": "",
    "watermark_required": true,
    "reference_links": [
      "https://www.mindful.org/what-is-mindfulness/",
      "https://www.ncbi.nlm.nih.gov/pmc/articles/PMC4940234/"
    ],
    "official_link": "",
    "supporting_link": "https://www.psychologytoday.com/us/basics/mindfulness",
    "word_count_target": "400-550",
    "article_html": "<p>In recent years, mindfulness has experienced a notable revival across a variety of spiritual traditions, finding renewed relevance in contemporary practice. Rooted in ancient contemplative disciplines, mindfulness involves a focused, non-judgmental awareness of the present moment. This simple yet profound practice has become a cornerstone in modern spiritual frameworks, offering a path toward enhanced mental well-being and ethical living.</p><p>Historically, mindfulness is deeply embedded in Buddhist meditation but its principles resonate beyond any single tradition. Today, it is increasingly integrated into diverse spiritual communities seeking to navigate the complexities of modern life. The fast pace and constant stimulation of contemporary society often contribute to stress, distraction, and a sense of disconnection. Mindfulness offers a counterbalance by encouraging individuals to slow down, observe their inner experiences, and cultivate a grounded presence.</p><p>One of the key contributions of mindfulness to modern spirituality is its emphasis on mental clarity and emotional regulation. By fostering awareness of thoughts and feelings without immediate reaction, practitioners develop greater resilience and compassion toward themselves and others. This shift supports not only personal mental health but also nurtures more harmonious relationships within communities. The ethical dimensions of mindfulness encourage intentional living, where actions are guided by awareness and empathy rather than impulse.</p><p>Moreover, mindfulness practices have been adapted to suit a range of spiritual contexts, from traditional meditation sessions to secular wellness programs. This flexibility has helped bridge ancient wisdom with contemporary needs, making mindfulness accessible without diluting its essence. Spiritual practitioners often report that mindfulness deepens their connection to a sense of purpose and meaning, reinforcing values such as patience, gratitude, and humility.</p><p>As mindfulness continues to permeate spiritual practice, it invites a reflective approach to how we engage with ourselves and the world. Rather than offering quick fixes, it cultivates a sustained attentiveness that supports ongoing growth and ethical awareness. In a world marked by rapid change and uncertainty, mindfulness remains a steady anchor, reminding us of the enduring power of presence.</p>"
  }
}