{
  "module_id": "AG60E",
  "title": "Article Index Verification Record",
  "status": "article_index_verified",
  "path": "data/article-index.json",
  "source_path": "data/article-index.json",
  "fetch_path_in_homepage": "data/article-index.json",
  "total": 148,
  "publicTotal": 77,
  "items_count": 148,
  "publishedItems_count": 77,
  "publicLatest_count": 8,
  "featuredReads_key_present": false,
  "sample_public_latest_title": "Advancing Digital Literacy through Public Education Programs",
  "conclusion": "The correct public article-index source is data/article-index.json. The earlier data/articles/index.json check was not the active homepage path."
}
